<keymap version="1" name="Mac OS X 10.5+ copy" parent="Mac OS X 10.5+">
  <action id="Git.ResolveConflicts">
    <keyboard-shortcut first-keystroke="ctrl meta alt r" />
  </action>
  <action id="RecentChangedFiles" />
  <action id="ReformatCode" />
  <action id="SplitVertically">
    <keyboard-shortcut first-keystroke="meta escape" />
  </action>
  <action id="SurroundWithEmmet">
    <keyboard-shortcut first-keystroke="shift meta e" />
  </action>
  <action id="SwitchApply">
    <keyboard-shortcut first-keystroke="ctrl alt enter" />
  </action>
  <action id="SwitchDown">
    <keyboard-shortcut first-keystroke="ctrl alt down" />
  </action>
  <action id="SwitchLeft">
    <keyboard-shortcut first-keystroke="ctrl alt left" />
  </action>
  <action id="SwitchRight">
    <keyboard-shortcut first-keystroke="ctrl alt right" />
  </action>
  <action id="SwitchUp">
    <keyboard-shortcut first-keystroke="ctrl alt up" />
  </action>
  <action id="Vcs.ReformatCommitMessage" />
  <action id="com.intellij.prettierjs.ReformatWithPrettierAction">
    <keyboard-shortcut first-keystroke="meta alt l" />
  </action>
  <action id="editRunConfigurations">
    <keyboard-shortcut first-keystroke="ctrl meta alt e" />
  </action>
</keymap>